LICENSE.txt
README.MD
setup.py
appwebshare/__init__.py
appwebshare/files.py
appwebshare/views.py
appwebshare/webshare.py
appwebshare/scripts/__init__.py
appwebshare/scripts/config.py
appwebshare/scripts/configme.py
appwebshare/scripts/run.py
appwebshare/templates/base.html
appwebshare/templates/index.html
appwebshare/templates/login.html
appwebshare/templates/search.html
appwebshare/tests/__init__.py
appwebshare/tests/test_webshare.py
webshare_download_manager.egg-info/PKG-INFO
webshare_download_manager.egg-info/SOURCES.txt
webshare_download_manager.egg-info/dependency_links.txt
webshare_download_manager.egg-info/entry_points.txt
webshare_download_manager.egg-info/not-zip-safe
webshare_download_manager.egg-info/requires.txt
webshare_download_manager.egg-info/top_level.txt