Metadata-Version: 1.0
Name: webshare-download-manager
Version: 0.2.6
Summary: Download manager for webshare.cz site. Flask + requests.
Home-page: https://github.com/cvakiitho/Webshare-download-manager
Author: Tomas Hartmann
Author-email: cvakiitho@gmail.com
License: LICENSE.txt
Platform: UNKNOWN
